truthnet/__init__.py
truthnet/truthfinder.py
truthnet/truthnet.py
truthnet/util.py
truthnet/.ipynb_checkpoints/validate-checkpoint.ipynb
truthnet/examples/calculate_response.ipynb
truthnet/examples/getAUClowerbnd.py
truthnet/examples/train_example.ipynb
truthnet/examples/validate.ipynb
truthnet/examples/validate_test.ipynb
truthnet/examples/validation_SUD.ipynb
truthnet/examples/validation_ptsd_1.ipynb
truthnet/examples/validation_ptsd_expt.ipynb
truthnet/examples/.ipynb_checkpoints/train_example-checkpoint.ipynb
truthnet/examples/.ipynb_checkpoints/validate-checkpoint.ipynb
truthnet/examples/.ipynb_checkpoints/validate_test-checkpoint.ipynb
truthnet-0.0.27.dist-info/LICENSE.md
truthnet-0.0.27.dist-info/METADATA
truthnet-0.0.27.dist-info/WHEEL
truthnet-0.0.27.dist-info/top_level.txt
truthnet-0.0.27.dist-info/RECORD
