Metadata-Version: 2.1
Name: truthnet
Version: 0.0.27
Summary: Algorithmic Lie Detector
Home-page: https://github.com/zeroknowledgediscovery/truthnet
Download-URL: https://github.com/zeroknowledgediscovery/truthnet/archive/ 0.0.27.tar.gz
Author: zed.uchicago.edu
Author-email: ishanu@uchicago.edu
License: LICENSE
Keywords: computational social science,decision trees,machine learning,malingering
Classifier: Development Status :: 4 - Beta
Classifier: Intended Audience :: Developers
Classifier: Intended Audience :: Science/Research
Classifier: Topic :: Scientific/Engineering :: Information Analysis
Classifier: Topic :: Software Development :: Libraries
Classifier: Programming Language :: Python :: 3.6
Requires-Python: >=3.6
License-File: LICENSE.md
Requires-Dist: scikit-learn
Requires-Dist: scipy
Requires-Dist: numpy
Requires-Dist: pandas
Requires-Dist: joblib
Requires-Dist: quasinet
